setup.py
tests/__init__.py
wsgi_seo_js/__init__.py
wsgi_seo_js.egg-info/PKG-INFO
wsgi_seo_js.egg-info/SOURCES.txt
wsgi_seo_js.egg-info/dependency_links.txt
wsgi_seo_js.egg-info/requires.txt
wsgi_seo_js.egg-info/top_level.txt