Metadata-Version: 1.1
Name: wsgi-seo-js
Version: 1.0.1
Summary: WSGI middleware that implements Google's Ajax Crawling specs
Home-page: http://github.com/alanjds/wsgi-seo-js
Author: Alan Justino da Silva
Author-email: alan.justino@yahoo.com.br
License: UNKNOWN
Platform: UNKNOWN
Classifier: Intended Audience :: Developers
Classifier: Operating System :: OS Independent
Classifier: Topic :: Software Development
